{
  "/_global-error/page": "app/_global-error/page.js",
  "/_not-found/page": "app/_not-found/page.js",
  "/api/auth/logout/route": "app/api/auth/logout/route.js",
  "/api/auth/me/route": "app/api/auth/me/route.js",
  "/api/auth/nonce/route": "app/api/auth/nonce/route.js",
  "/api/auth/verify/route": "app/api/auth/verify/route.js",
  "/api/offers/[id]/route": "app/api/offers/[id]/route.js",
  "/api/offers/active/route": "app/api/offers/active/route.js",
  "/api/offers/route": "app/api/offers/route.js",
  "/api/offers/seller/[seller]/route": "app/api/offers/seller/[seller]/route.js",
  "/api/proposals/[id]/route": "app/api/proposals/[id]/route.js",
  "/api/proposals/buyer/[buyer]/route": "app/api/proposals/buyer/[buyer]/route.js",
  "/api/proposals/offer/[offer_id]/route": "app/api/proposals/offer/[offer_id]/route.js",
  "/api/proposals/pending/route": "app/api/proposals/pending/route.js",
  "/api/proposals/route": "app/api/proposals/route.js",
  "/api/proxy-metadata/route": "app/api/proxy-metadata/route.js",
  "/api/swaps/[id]/route": "app/api/swaps/[id]/route.js",
  "/api/swaps/buyer/[buyer]/route": "app/api/swaps/buyer/[buyer]/route.js",
  "/api/swaps/recent/route": "app/api/swaps/recent/route.js",
  "/api/swaps/route": "app/api/swaps/route.js",
  "/api/swaps/seller/[seller]/route": "app/api/swaps/seller/[seller]/route.js",
  "/api/swaps/stats/route": "app/api/swaps/stats/route.js",
  "/create-offer/page": "app/create-offer/page.js",
  "/dashboard/page": "app/dashboard/page.js",
  "/favicon.ico/route": "app/favicon.ico/route.js",
  "/marketplace/page": "app/marketplace/page.js",
  "/page": "app/page.js"
}